{"frames": {

"hellhound_WIP":
{
	"frame": {"x":2,"y":2,"w":957,"h":282},
	"rotated": false,
	"trimmed": false,
	"spriteSourceSize": {"x":0,"y":0,"w":957,"h":282},
	"sourceSize": {"w":957,"h":282},
	"pivot": {"x":0.5,"y":0.5}
},
"hellhound_idle_01":
{
	"frame": {"x":1574,"y":370,"w":110,"h":52},
	"rotated": false,
	"trimmed": false,
	"spriteSourceSize": {"x":0,"y":0,"w":110,"h":52},
	"sourceSize": {"w":110,"h":52},
	"pivot": {"x":0.5,"y":0.5}
},
"hellhound_walking_02":
{
	"frame": {"x":1574,"y":424,"w":110,"h":51},
	"rotated": false,
	"trimmed": false,
	"spriteSourceSize": {"x":0,"y":0,"w":110,"h":51},
	"sourceSize": {"w":110,"h":51},
	"pivot": {"x":0.5,"y":0.5}
},
"hellhound_walking_03":
{
	"frame": {"x":1587,"y":278,"w":109,"h":52},
	"rotated": false,
	"trimmed": false,
	"spriteSourceSize": {"x":0,"y":0,"w":109,"h":52},
	"sourceSize": {"w":109,"h":52},
	"pivot": {"x":0.5,"y":0.5}
},
"skwar_idle_01":
{
	"frame": {"x":479,"y":384,"w":104,"h":96},
	"rotated": false,
	"trimmed": false,
	"spriteSourceSize": {"x":0,"y":0,"w":104,"h":96},
	"sourceSize": {"w":104,"h":96},
	"pivot": {"x":0.5,"y":0.5}
},
"skwar_slash_01":
{
	"frame": {"x":324,"y":384,"w":153,"h":96},
	"rotated": false,
	"trimmed": false,
	"spriteSourceSize": {"x":0,"y":0,"w":153,"h":96},
	"sourceSize": {"w":153,"h":96},
	"pivot": {"x":0.5,"y":0.5}
},
"skwar_slash_02":
{
	"frame": {"x":2,"y":286,"w":159,"h":96},
	"rotated": false,
	"trimmed": false,
	"spriteSourceSize": {"x":0,"y":0,"w":159,"h":96},
	"sourceSize": {"w":159,"h":96},
	"pivot": {"x":0.5,"y":0.5}
},
"skwar_slash_03":
{
	"frame": {"x":2,"y":384,"w":159,"h":96},
	"rotated": false,
	"trimmed": false,
	"spriteSourceSize": {"x":0,"y":0,"w":159,"h":96},
	"sourceSize": {"w":159,"h":96},
	"pivot": {"x":0.5,"y":0.5}
},
"skwar_slash_04":
{
	"frame": {"x":163,"y":286,"w":159,"h":96},
	"rotated": false,
	"trimmed": false,
	"spriteSourceSize": {"x":0,"y":0,"w":159,"h":96},
	"sourceSize": {"w":159,"h":96},
	"pivot": {"x":0.5,"y":0.5}
},
"skwar_slash_05":
{
	"frame": {"x":163,"y":384,"w":159,"h":96},
	"rotated": false,
	"trimmed": false,
	"spriteSourceSize": {"x":0,"y":0,"w":159,"h":96},
	"sourceSize": {"w":159,"h":96},
	"pivot": {"x":0.5,"y":0.5}
},
"skwar_slash_06":
{
	"frame": {"x":324,"y":286,"w":159,"h":96},
	"rotated": false,
	"trimmed": false,
	"spriteSourceSize": {"x":0,"y":0,"w":159,"h":96},
	"sourceSize": {"w":159,"h":96},
	"pivot": {"x":0.5,"y":0.5}
},
"skwar_walking_01":
{
	"frame": {"x":485,"y":286,"w":104,"h":96},
	"rotated": false,
	"trimmed": false,
	"spriteSourceSize": {"x":0,"y":0,"w":104,"h":96},
	"sourceSize": {"w":104,"h":96},
	"pivot": {"x":0.5,"y":0.5}
},
"skwar_walking_02":
{
	"frame": {"x":585,"y":384,"w":104,"h":96},
	"rotated": false,
	"trimmed": false,
	"spriteSourceSize": {"x":0,"y":0,"w":104,"h":96},
	"sourceSize": {"w":104,"h":96},
	"pivot": {"x":0.5,"y":0.5}
},
"skwar_walking_03":
{
	"frame": {"x":591,"y":286,"w":104,"h":96},
	"rotated": false,
	"trimmed": false,
	"spriteSourceSize": {"x":0,"y":0,"w":104,"h":96},
	"sourceSize": {"w":104,"h":96},
	"pivot": {"x":0.5,"y":0.5}
},
"skwar_walking_04":
{
	"frame": {"x":691,"y":384,"w":104,"h":96},
	"rotated": false,
	"trimmed": false,
	"spriteSourceSize": {"x":0,"y":0,"w":104,"h":96},
	"sourceSize": {"w":104,"h":96},
	"pivot": {"x":0.5,"y":0.5}
},
"skwar_walking_05":
{
	"frame": {"x":697,"y":286,"w":104,"h":96},
	"rotated": false,
	"trimmed": false,
	"spriteSourceSize": {"x":0,"y":0,"w":104,"h":96},
	"sourceSize": {"w":104,"h":96},
	"pivot": {"x":0.5,"y":0.5}
},
"skwar_walking_06":
{
	"frame": {"x":797,"y":384,"w":104,"h":96},
	"rotated": false,
	"trimmed": false,
	"spriteSourceSize": {"x":0,"y":0,"w":104,"h":96},
	"sourceSize": {"w":104,"h":96},
	"pivot": {"x":0.5,"y":0.5}
},
"skwar_walking_07":
{
	"frame": {"x":803,"y":286,"w":104,"h":96},
	"rotated": false,
	"trimmed": false,
	"spriteSourceSize": {"x":0,"y":0,"w":104,"h":96},
	"sourceSize": {"w":104,"h":96},
	"pivot": {"x":0.5,"y":0.5}
},
"skwar_walking_08":
{
	"frame": {"x":903,"y":384,"w":104,"h":96},
	"rotated": false,
	"trimmed": false,
	"spriteSourceSize": {"x":0,"y":0,"w":104,"h":96},
	"sourceSize": {"w":104,"h":96},
	"pivot": {"x":0.5,"y":0.5}
},
"strider_idle_01":
{
	"frame": {"x":1235,"y":380,"w":111,"h":90},
	"rotated": false,
	"trimmed": false,
	"spriteSourceSize": {"x":0,"y":0,"w":111,"h":90},
	"sourceSize": {"w":111,"h":90},
	"pivot": {"x":0.5,"y":0.5}
},
"strider_idle_02":
{
	"frame": {"x":1187,"y":2,"w":111,"h":90},
	"rotated": false,
	"trimmed": false,
	"spriteSourceSize": {"x":0,"y":0,"w":111,"h":90},
	"sourceSize": {"w":111,"h":90},
	"pivot": {"x":0.5,"y":0.5}
},
"strider_idle_03":
{
	"frame": {"x":1187,"y":94,"w":111,"h":90},
	"rotated": false,
	"trimmed": false,
	"spriteSourceSize": {"x":0,"y":0,"w":111,"h":90},
	"sourceSize": {"w":111,"h":90},
	"pivot": {"x":0.5,"y":0.5}
},
"strider_idle_04":
{
	"frame": {"x":1187,"y":186,"w":111,"h":90},
	"rotated": false,
	"trimmed": false,
	"spriteSourceSize": {"x":0,"y":0,"w":111,"h":90},
	"sourceSize": {"w":111,"h":90},
	"pivot": {"x":0.5,"y":0.5}
},
"strider_idle_05":
{
	"frame": {"x":1074,"y":192,"w":111,"h":91},
	"rotated": false,
	"trimmed": false,
	"spriteSourceSize": {"x":0,"y":0,"w":111,"h":91},
	"sourceSize": {"w":111,"h":91},
	"pivot": {"x":0.5,"y":0.5}
},
"strider_idle_06":
{
	"frame": {"x":1248,"y":278,"w":111,"h":90},
	"rotated": false,
	"trimmed": false,
	"spriteSourceSize": {"x":0,"y":0,"w":111,"h":90},
	"sourceSize": {"w":111,"h":90},
	"pivot": {"x":0.5,"y":0.5}
},
"strider_idle_07":
{
	"frame": {"x":1348,"y":370,"w":111,"h":90},
	"rotated": false,
	"trimmed": false,
	"spriteSourceSize": {"x":0,"y":0,"w":111,"h":90},
	"sourceSize": {"w":111,"h":90},
	"pivot": {"x":0.5,"y":0.5}
},
"strider_idle_08":
{
	"frame": {"x":1461,"y":2,"w":111,"h":90},
	"rotated": false,
	"trimmed": false,
	"spriteSourceSize": {"x":0,"y":0,"w":111,"h":90},
	"sourceSize": {"w":111,"h":90},
	"pivot": {"x":0.5,"y":0.5}
},
"strider_idle_09":
{
	"frame": {"x":1574,"y":2,"w":111,"h":90},
	"rotated": false,
	"trimmed": false,
	"spriteSourceSize": {"x":0,"y":0,"w":111,"h":90},
	"sourceSize": {"w":111,"h":90},
	"pivot": {"x":0.5,"y":0.5}
},
"strider_idle_10":
{
	"frame": {"x":1300,"y":2,"w":111,"h":90},
	"rotated": false,
	"trimmed": false,
	"spriteSourceSize": {"x":0,"y":0,"w":111,"h":90},
	"sourceSize": {"w":111,"h":90},
	"pivot": {"x":0.5,"y":0.5}
},
"strider_idle_11":
{
	"frame": {"x":1300,"y":94,"w":111,"h":90},
	"rotated": false,
	"trimmed": false,
	"spriteSourceSize": {"x":0,"y":0,"w":111,"h":90},
	"sourceSize": {"w":111,"h":90},
	"pivot": {"x":0.5,"y":0.5}
},
"strider_idle_12":
{
	"frame": {"x":1300,"y":186,"w":111,"h":90},
	"rotated": false,
	"trimmed": false,
	"spriteSourceSize": {"x":0,"y":0,"w":111,"h":90},
	"sourceSize": {"w":111,"h":90},
	"pivot": {"x":0.5,"y":0.5}
},
"strider_idle_13":
{
	"frame": {"x":1361,"y":278,"w":111,"h":90},
	"rotated": false,
	"trimmed": false,
	"spriteSourceSize": {"x":0,"y":0,"w":111,"h":90},
	"sourceSize": {"w":111,"h":90},
	"pivot": {"x":0.5,"y":0.5}
},
"strider_idle_14":
{
	"frame": {"x":1461,"y":370,"w":111,"h":90},
	"rotated": false,
	"trimmed": false,
	"spriteSourceSize": {"x":0,"y":0,"w":111,"h":90},
	"sourceSize": {"w":111,"h":90},
	"pivot": {"x":0.5,"y":0.5}
},
"strider_idle_15":
{
	"frame": {"x":1574,"y":94,"w":111,"h":90},
	"rotated": false,
	"trimmed": false,
	"spriteSourceSize": {"x":0,"y":0,"w":111,"h":90},
	"sourceSize": {"w":111,"h":90},
	"pivot": {"x":0.5,"y":0.5}
},
"strider_idle_16":
{
	"frame": {"x":1413,"y":186,"w":111,"h":90},
	"rotated": false,
	"trimmed": false,
	"spriteSourceSize": {"x":0,"y":0,"w":111,"h":90},
	"sourceSize": {"w":111,"h":90},
	"pivot": {"x":0.5,"y":0.5}
},
"strider_idle_17":
{
	"frame": {"x":1413,"y":94,"w":111,"h":90},
	"rotated": false,
	"trimmed": false,
	"spriteSourceSize": {"x":0,"y":0,"w":111,"h":90},
	"sourceSize": {"w":111,"h":90},
	"pivot": {"x":0.5,"y":0.5}
},
"strider_idle_18":
{
	"frame": {"x":1474,"y":278,"w":111,"h":90},
	"rotated": false,
	"trimmed": false,
	"spriteSourceSize": {"x":0,"y":0,"w":111,"h":90},
	"sourceSize": {"w":111,"h":90},
	"pivot": {"x":0.5,"y":0.5}
},
"strider_idle_19":
{
	"frame": {"x":1526,"y":186,"w":111,"h":90},
	"rotated": false,
	"trimmed": false,
	"spriteSourceSize": {"x":0,"y":0,"w":111,"h":90},
	"sourceSize": {"w":111,"h":90},
	"pivot": {"x":0.5,"y":0.5}
},
"strider_walking_01":
{
	"frame": {"x":961,"y":2,"w":111,"h":93},
	"rotated": false,
	"trimmed": false,
	"spriteSourceSize": {"x":0,"y":0,"w":111,"h":93},
	"sourceSize": {"w":111,"h":93},
	"pivot": {"x":0.5,"y":0.5}
},
"strider_walking_02":
{
	"frame": {"x":961,"y":192,"w":111,"h":92},
	"rotated": false,
	"trimmed": false,
	"spriteSourceSize": {"x":0,"y":0,"w":111,"h":92},
	"sourceSize": {"w":111,"h":92},
	"pivot": {"x":0.5,"y":0.5}
},
"strider_walking_03":
{
	"frame": {"x":961,"y":97,"w":111,"h":93},
	"rotated": false,
	"trimmed": false,
	"spriteSourceSize": {"x":0,"y":0,"w":111,"h":93},
	"sourceSize": {"w":111,"h":93},
	"pivot": {"x":0.5,"y":0.5}
},
"strider_walking_04":
{
	"frame": {"x":1022,"y":286,"w":111,"h":93},
	"rotated": false,
	"trimmed": false,
	"spriteSourceSize": {"x":0,"y":0,"w":111,"h":93},
	"sourceSize": {"w":111,"h":93},
	"pivot": {"x":0.5,"y":0.5}
},
"strider_walking_05":
{
	"frame": {"x":1122,"y":381,"w":111,"h":93},
	"rotated": false,
	"trimmed": false,
	"spriteSourceSize": {"x":0,"y":0,"w":111,"h":93},
	"sourceSize": {"w":111,"h":93},
	"pivot": {"x":0.5,"y":0.5}
},
"strider_walking_06":
{
	"frame": {"x":1074,"y":2,"w":111,"h":93},
	"rotated": false,
	"trimmed": false,
	"spriteSourceSize": {"x":0,"y":0,"w":111,"h":93},
	"sourceSize": {"w":111,"h":93},
	"pivot": {"x":0.5,"y":0.5}
},
"strider_walking_07":
{
	"frame": {"x":1074,"y":97,"w":111,"h":93},
	"rotated": false,
	"trimmed": false,
	"spriteSourceSize": {"x":0,"y":0,"w":111,"h":93},
	"sourceSize": {"w":111,"h":93},
	"pivot": {"x":0.5,"y":0.5}
},
"strider_walking_08":
{
	"frame": {"x":909,"y":286,"w":111,"h":94},
	"rotated": false,
	"trimmed": false,
	"spriteSourceSize": {"x":0,"y":0,"w":111,"h":94},
	"sourceSize": {"w":111,"h":94},
	"pivot": {"x":0.5,"y":0.5}
},
"strider_walking_09":
{
	"frame": {"x":1009,"y":382,"w":111,"h":94},
	"rotated": false,
	"trimmed": false,
	"spriteSourceSize": {"x":0,"y":0,"w":111,"h":94},
	"sourceSize": {"w":111,"h":94},
	"pivot": {"x":0.5,"y":0.5}
},
"strider_walking_10":
{
	"frame": {"x":1135,"y":285,"w":111,"h":93},
	"rotated": false,
	"trimmed": false,
	"spriteSourceSize": {"x":0,"y":0,"w":111,"h":93},
	"sourceSize": {"w":111,"h":93},
	"pivot": {"x":0.5,"y":0.5}
}},
"meta": {
	"app": "http://www.codeandweb.com/texturepacker",
	"version": "1.0",
	"image": "strider.png",
	"format": "RGBA8888",
	"size": {"w":1698,"h":482},
	"scale": "1",
	"smartupdate": "$TexturePacker:SmartUpdate:c937a1be2173344ce6a97fc4466e23a1:09b351ec94f8da8bff6d76716ddc611e:349587be09db1d83b8c05ffd2a6370ca$"
}
}
